fastapi_react_cli.py
fastapi_react_web-0.1.2.dist-info/METADATA
fastapi_react_web-0.1.2.dist-info/WHEEL
fastapi_react_web-0.1.2.dist-info/entry_points.txt
fastapi_react_web-0.1.2.dist-info/top_level.txt
fastapi_react_web-0.1.2.dist-info/RECORD
