Metadata-Version: 2.4
Name: fastapi-react-web
Version: 0.1.2
Summary: FastAPI + React project setup CLI
Author: Rudraksh121a
License: MIT
Requires-Dist: fastapi
Requires-Dist: uvicorn
Requires-Dist: setuptools
